idpalette/__init__.py
idpalette-0.1.0.dist-info/METADATA
idpalette-0.1.0.dist-info/WHEEL
idpalette-0.1.0.dist-info/licenses/LICENSE
idpalette-0.1.0.dist-info/RECORD
