Metadata-Version: 2.3
Name: idpalette
Version: 0.1.0
Summary: Colour palettes based on the ACEFA, IDDU, and IDEM logos
Project-URL: Homepage, https://github.com/robmoss/idpalette/
Project-URL: Repository, https://github.com/robmoss/idpalette/
Author-email: Rob Moss <rgmoss@unimelb.edu.au>
Maintainer-email: Rob Moss <rgmoss@unimelb.edu.au>
License: Copyright (c) 2024, Rob Moss
License-File: LICENSE
Requires-Python: >=3.8
Requires-Dist: mizani~=0.11
Provides-Extra: cmap
Requires-Dist: matplotlib~=3.9; extra == 'cmap'
Provides-Extra: tests
Requires-Dist: pytest; extra == 'tests'
Requires-Dist: pytest-cov~=4.0; extra == 'tests'
